[{"Action":"Action shot","Cap":6.0,"Game":1,"JPN":0,"Opponent":0,"Opponent name":"ITA","Period":1.0,"Player":"TAKAHASHI A","Score":"0 - 0","Seconds":443,"Team":"JPN","Time":"7:23","Result":"Post","Goal":0},{"Action":"Extra player shot","Cap":3.0,"Game":1,"JPN":0,"Opponent":1,"Opponent name":"ITA","Period":1.0,"Player":"GARIBOTTI A","Score":"0 - 1","Seconds":412,"Team":"ITA","Time":"6:52","Result":"Goal","Goal":1},{"Action":"Extra player shot","Cap":9.0,"Game":1,"JPN":0,"Opponent":2,"Opponent name":"ITA","Period":1.0,"Player":"EMMOLO G","Score":"0 - 2","Seconds":361,"Team":"ITA","Time":"6:01","Result":"Goal","Goal":1},{"Action":"Extra player shot","Cap":7.0,"Game":1,"JPN":0,"Opponent":2,"Opponent name":"ITA","Period":1.0,"Player":"NAKANO Y","Score":"0 - 2","Seconds":292,"Team":"JPN","Time":"4:52","Result":"Saved","Goal":0},{"Action":"Penalty shot","Cap":8.0,"Game":1,"JPN":0,"Opponent":2,"Opponent name":"ITA","Period":1.0,"Player":"HASHIGUCHI M","Score":"0 - 2","Seconds":213,"Team":"JPN","Time":"3:33","Result":"Saved","Goal":0},{"Action":"Action shot","Cap":8.0,"Game":1,"JPN":0,"Opponent":3,"Opponent name":"ITA","Period":1.0,"Player":"BIANCONI R","Score":"0 - 3","Seconds":183,"Team":"ITA","Time":"3:03","Result":"Goal","Goal":1},{"Action":"Centre shot","Cap":6.0,"Game":1,"JPN":0,"Opponent":4,"Opponent name":"ITA","Period":1.0,"Player":"AIELLO R","Score":"0 - 4","Seconds":92,"Team":"ITA","Time":"1:32","Result":"Goal","Goal":1},{"Action":"Extra player shot","Cap":11.0,"Game":1,"JPN":0,"Opponent":5,"Opponent name":"ITA","Period":1.0,"Player":"BARZON L","Score":"0 - 5","Seconds":25,"Team":"ITA","Time":"0:25","Result":"Goal","Goal":1},{"Action":"Action shot","Cap":3.0,"Game":1,"JPN":0,"Opponent":5,"Opponent name":"ITA","Period":2.0,"Player":"KAZAMA Y","Score":"0 - 5","Seconds":432,"Team":"JPN","Time":"7:12","Result":"Saved","Goal":0},{"Action":"Action shot","Cap":10.0,"Game":1,"JPN":0,"Opponent":5,"Opponent name":"ITA","Period":2.0,"Player":"MORI T","Score":"0 - 5","Seconds":372,"Team":"JPN","Time":"6:12","Result":"Blocked","Goal":0},{"Action":"Extra player shot","Cap":3.0,"Game":1,"JPN":0,"Opponent":6,"Opponent name":"ITA","Period":2.0,"Player":"GARIBOTTI A","Score":"0 - 6","Seconds":329,"Team":"ITA","Time":"5:29","Result":"Goal","Goal":1},{"Action":"5m shot","Cap":10.0,"Game":1,"JPN":0,"Opponent":6,"Opponent name":"ITA","Period":2.0,"Player":"MORI T","Score":"0 - 6","Seconds":258,"Team":"JPN","Time":"4:18","Result":"Post","Goal":0},{"Action":"Action shot","Cap":3.0,"Game":1,"JPN":1,"Opponent":6,"Opponent name":"ITA","Period":2.0,"Player":"KAZAMA Y","Score":"1 - 6","Seconds":230,"Team":"JPN","Time":"3:50","Result":"Goal","Goal":1},{"Action":"Action shot","Cap":2.0,"Game":1,"JPN":1,"Opponent":7,"Opponent name":"ITA","Period":2.0,"Player":"TABANI C","Score":"1 - 7","Seconds":202,"Team":"ITA","Time":"3:22","Result":"Goal","Goal":1},{"Action":"Action shot","Cap":9.0,"Game":1,"JPN":1,"Opponent":7,"Opponent name":"ITA","Period":2.0,"Player":"EMMOLO G","Score":"1 - 7","Seconds":156,"Team":"ITA","Time":"2:36","Result":"Saved","Goal":0},{"Action":"Action shot","Cap":8.0,"Game":1,"JPN":1,"Opponent":7,"Opponent name":"ITA","Period":2.0,"Player":"HASHIGUCHI M","Score":"1 - 7","Seconds":131,"Team":"JPN","Time":"2:11","Result":"Post","Goal":0},{"Action":"Action shot","Cap":4.0,"Game":1,"JPN":1,"Opponent":7,"Opponent name":"ITA","Period":2.0,"Player":"QUEIROLO E","Score":"1 - 7","Seconds":113,"Team":"ITA","Time":"1:53","Result":"Saved","Goal":0},{"Action":"Action shot","Cap":11.0,"Game":1,"JPN":1,"Opponent":8,"Opponent name":"ITA","Period":2.0,"Player":"BARZON L","Score":"1 - 8","Seconds":68,"Team":"ITA","Time":"1:08","Result":"Goal","Goal":1},{"Action":"Action shot","Cap":5.0,"Game":1,"JPN":1,"Opponent":8,"Opponent name":"ITA","Period":2.0,"Player":"NAKATA M","Score":"1 - 8","Seconds":36,"Team":"JPN","Time":"0:36","Result":"Post","Goal":0},{"Action":"5m shot","Cap":2.0,"Game":1,"JPN":1,"Opponent":8,"Opponent name":"ITA","Period":2.0,"Player":"SAKANOUE C","Score":"1 - 8","Seconds":1,"Team":"JPN","Time":"0:01","Result":"Saved","Goal":0},{"Action":"Action shot","Cap":3.0,"Game":1,"JPN":1,"Opponent":8,"Opponent name":"ITA","Period":3.0,"Player":"KAZAMA Y","Score":"1 - 8","Seconds":441,"Team":"JPN","Time":"7:21","Result":"Saved","Goal":0},{"Action":"Action shot","Cap":12.0,"Game":1,"JPN":1,"Opponent":8,"Opponent name":"ITA","Period":3.0,"Player":"FRASSINETTI T","Score":"1 - 8","Seconds":416,"Team":"ITA","Time":"6:56","Result":"Post","Goal":0},{"Action":"Action shot","Cap":2.0,"Game":1,"JPN":1,"Opponent":8,"Opponent name":"ITA","Period":3.0,"Player":"SAKANOUE C","Score":"1 - 8","Seconds":400,"Team":"JPN","Time":"6:40","Result":"Post","Goal":0},{"Action":"Extra player shot","Cap":10.0,"Game":1,"JPN":1,"Opponent":8,"Opponent name":"ITA","Period":3.0,"Player":"MORI T","Score":"1 - 8","Seconds":366,"Team":"JPN","Time":"6:06","Result":"Post","Goal":0},{"Action":"5m shot","Cap":7.0,"Game":1,"JPN":1,"Opponent":9,"Opponent name":"ITA","Period":3.0,"Player":"DI MARIO T","Score":"1 - 9","Seconds":341,"Team":"ITA","Time":"5:41","Result":"Goal","Goal":1},{"Action":"Action shot","Cap":9.0,"Game":1,"JPN":1,"Opponent":9,"Opponent name":"ITA","Period":3.0,"Player":"HOSOYA K","Score":"1 - 9","Seconds":296,"Team":"JPN","Time":"4:56","Result":"Post","Goal":0},{"Action":"Action shot","Cap":9.0,"Game":1,"JPN":1,"Opponent":9,"Opponent name":"ITA","Period":3.0,"Player":"HOSOYA K","Score":"1 - 9","Seconds":287,"Team":"JPN","Time":"4:47","Result":"Saved","Goal":0},{"Action":"Action shot","Cap":10.0,"Game":1,"JPN":2,"Opponent":9,"Opponent name":"ITA","Period":3.0,"Player":"MORI T","Score":"2 - 9","Seconds":275,"Team":"JPN","Time":"4:35","Result":"Goal","Goal":1},{"Action":"Action shot","Cap":2.0,"Game":1,"JPN":3,"Opponent":9,"Opponent name":"ITA","Period":3.0,"Player":"SAKANOUE C","Score":"3 - 9","Seconds":221,"Team":"JPN","Time":"3:41","Result":"Goal","Goal":1},{"Action":"Action shot","Cap":4.0,"Game":1,"JPN":3,"Opponent":10,"Opponent name":"ITA","Period":3.0,"Player":"QUEIROLO E","Score":"3 - 10","Seconds":204,"Team":"ITA","Time":"3:24","Result":"Goal","Goal":1},{"Action":"5m shot","Cap":7.0,"Game":1,"JPN":3,"Opponent":10,"Opponent name":"ITA","Period":3.0,"Player":"NAKANO Y","Score":"3 - 10","Seconds":175,"Team":"JPN","Time":"2:55","Result":"Saved","Goal":0},{"Action":"Action shot","Cap":11.0,"Game":1,"JPN":3,"Opponent":10,"Opponent name":"ITA","Period":3.0,"Player":"BARZON L","Score":"3 - 10","Seconds":130,"Team":"ITA","Time":"2:10","Result":"Saved","Goal":0},{"Action":"5m shot","Cap":7.0,"Game":1,"JPN":3,"Opponent":10,"Opponent name":"ITA","Period":3.0,"Player":"NAKANO Y","Score":"3 - 10","Seconds":102,"Team":"JPN","Time":"1:42","Result":"Post","Goal":0},{"Action":"5m shot","Cap":9.0,"Game":1,"JPN":3,"Opponent":10,"Opponent name":"ITA","Period":3.0,"Player":"EMMOLO G","Score":"3 - 10","Seconds":1,"Team":"ITA","Time":"0:01","Result":"Missed","Goal":0},{"Action":"Action shot","Cap":3.0,"Game":1,"JPN":3,"Opponent":11,"Opponent name":"ITA","Period":4.0,"Player":"GARIBOTTI A","Score":"3 - 11","Seconds":420,"Team":"ITA","Time":"7:00","Result":"Goal","Goal":1},{"Action":"Extra player shot","Cap":7.0,"Game":1,"JPN":3,"Opponent":11,"Opponent name":"ITA","Period":4.0,"Player":"NAKANO Y","Score":"3 - 11","Seconds":382,"Team":"JPN","Time":"6:22","Result":"Saved","Goal":0},{"Action":"5m shot","Cap":8.0,"Game":1,"JPN":3,"Opponent":12,"Opponent name":"ITA","Period":4.0,"Player":"BIANCONI R","Score":"3 - 12","Seconds":362,"Team":"ITA","Time":"6:02","Result":"Goal","Goal":1},{"Action":"Action shot","Cap":10.0,"Game":1,"JPN":3,"Opponent":12,"Opponent name":"ITA","Period":4.0,"Player":"MORI T","Score":"3 - 12","Seconds":332,"Team":"JPN","Time":"5:32","Result":"Saved","Goal":0},{"Action":"Penalty shot","Cap":4.0,"Game":1,"JPN":3,"Opponent":13,"Opponent name":"ITA","Period":4.0,"Player":"QUEIROLO E","Score":"3 - 13","Seconds":310,"Team":"ITA","Time":"5:10","Result":"Goal","Goal":1},{"Action":"5m shot","Cap":8.0,"Game":1,"JPN":3,"Opponent":13,"Opponent name":"ITA","Period":4.0,"Player":"HASHIGUCHI M","Score":"3 - 13","Seconds":279,"Team":"JPN","Time":"4:39","Result":"Saved","Goal":0},{"Action":"Penalty shot","Cap":8.0,"Game":1,"JPN":3,"Opponent":13,"Opponent name":"ITA","Period":4.0,"Player":"HASHIGUCHI M","Score":"3 - 13","Seconds":252,"Team":"JPN","Time":"4:12","Result":"Saved","Goal":0},{"Action":"5m shot","Cap":10.0,"Game":1,"JPN":3,"Opponent":13,"Opponent name":"ITA","Period":4.0,"Player":"MORI T","Score":"3 - 13","Seconds":222,"Team":"JPN","Time":"3:42","Result":"Blocked","Goal":0},{"Action":"5m shot","Cap":2.0,"Game":1,"JPN":3,"Opponent":14,"Opponent name":"ITA","Period":4.0,"Player":"TABANI C","Score":"3 - 14","Seconds":206,"Team":"ITA","Time":"3:26","Result":"Goal","Goal":1},{"Action":"Action shot","Cap":6.0,"Game":1,"JPN":3,"Opponent":14,"Opponent name":"ITA","Period":4.0,"Player":"AIELLO R","Score":"3 - 14","Seconds":163,"Team":"ITA","Time":"2:43","Result":"Saved","Goal":0},{"Action":"Extra player shot","Cap":4.0,"Game":1,"JPN":3,"Opponent":14,"Opponent name":"ITA","Period":4.0,"Player":"MAGARIYAMA S","Score":"3 - 14","Seconds":124,"Team":"JPN","Time":"2:04","Result":"Saved","Goal":0},{"Action":"Action shot","Cap":2.0,"Game":1,"JPN":3,"Opponent":15,"Opponent name":"ITA","Period":4.0,"Player":"TABANI C","Score":"3 - 15","Seconds":58,"Team":"ITA","Time":"0:58","Result":"Goal","Goal":1},{"Action":"Action shot","Cap":5.0,"Game":1,"JPN":3,"Opponent":15,"Opponent name":"ITA","Period":4.0,"Player":"NAKATA M","Score":"3 - 15","Seconds":29,"Team":"JPN","Time":"0:29","Result":"Saved","Goal":0},{"Action":"Action shot","Cap":3.0,"Game":1,"JPN":3,"Opponent":15,"Opponent name":"ITA","Period":4.0,"Player":"GARIBOTTI A","Score":"3 - 15","Seconds":1,"Team":"ITA","Time":"0:01","Result":"Saved","Goal":0},{"Action":"Extra player shot","Cap":6.0,"Game":2,"JPN":0,"Opponent":0,"Opponent name":"BRA","Period":1.0,"Player":"CHIAPPINI I","Score":"0 - 0","Seconds":451,"Team":"BRA","Time":"7:31","Result":"Saved","Goal":0},{"Action":"Centre shot","Cap":6.0,"Game":2,"JPN":0,"Opponent":1,"Opponent name":"BRA","Period":1.0,"Player":"CHIAPPINI I","Score":"1 - 0","Seconds":436,"Team":"BRA","Time":"7:16","Result":"Goal","Goal":1},{"Action":"Centre shot","Cap":9.0,"Game":2,"JPN":0,"Opponent":2,"Opponent name":"BRA","Period":1.0,"Player":"DIAS M","Score":"2 - 0","Seconds":403,"Team":"BRA","Time":"6:43","Result":"Goal","Goal":1},{"Action":"Extra player shot","Cap":10.0,"Game":2,"JPN":0,"Opponent":2,"Opponent name":"BRA","Period":1.0,"Player":"MORI T","Score":"2 - 0","Seconds":326,"Team":"JPN","Time":"5:26","Result":"Blocked","Goal":0},{"Action":"Action shot","Cap":7.0,"Game":2,"JPN":0,"Opponent":2,"Opponent name":"BRA","Period":1.0,"Player":"NAKANO Y","Score":"2 - 0","Seconds":312,"Team":"JPN","Time":"5:12","Result":"Saved","Goal":0},{"Action":"Action shot","Cap":11.0,"Game":2,"JPN":0,"Opponent":2,"Opponent name":"BRA","Period":1.0,"Player":"TOKUMOTO M","Score":"2 - 0","Seconds":302,"Team":"JPN","Time":"5:02","Result":"Saved","Goal":0},{"Action":"Action shot","Cap":7.0,"Game":2,"JPN":0,"Opponent":2,"Opponent name":"BRA","Period":1.0,"Player":"NAKANO Y","Score":"2 - 0","Seconds":265,"Team":"JPN","Time":"4:25","Result":"Blocked","Goal":0},{"Action":"Counter attack","Cap":7.0,"Game":2,"JPN":1,"Opponent":2,"Opponent name":"BRA","Period":1.0,"Player":"NAKANO Y","Score":"2 - 1","Seconds":221,"Team":"JPN","Time":"3:41","Result":"Goal","Goal":1},{"Action":"Extra player shot","Cap":12.0,"Game":2,"JPN":1,"Opponent":3,"Opponent name":"BRA","Period":1.0,"Player":"MANTELLATO G","Score":"3 - 1","Seconds":181,"Team":"BRA","Time":"3:01","Result":"Goal","Goal":1},{"Action":"Penalty shot","Cap":6.0,"Game":2,"JPN":1,"Opponent":4,"Opponent name":"BRA","Period":1.0,"Player":"CHIAPPINI I","Score":"4 - 1","Seconds":130,"Team":"BRA","Time":"2:10","Result":"Goal","Goal":1},{"Action":"5m shot","Cap":7.0,"Game":2,"JPN":1,"Opponent":4,"Opponent name":"BRA","Period":1.0,"Player":"NAKANO Y","Score":"4 - 1","Seconds":108,"Team":"JPN","Time":"1:48","Result":"Post","Goal":0},{"Action":"5m shot","Cap":7.0,"Game":2,"JPN":1,"Opponent":4,"Opponent name":"BRA","Period":1.0,"Player":"NAKANO Y","Score":"4 - 1","Seconds":59,"Team":"JPN","Time":"0:59","Result":"Post","Goal":0},{"Action":"Action shot","Cap":6.0,"Game":2,"JPN":2,"Opponent":4,"Opponent name":"BRA","Period":1.0,"Player":"TAKAHASHI A","Score":"4 - 2","Seconds":26,"Team":"JPN","Time":"0:26","Result":"Goal","Goal":1},{"Action":"Action shot","Cap":4.0,"Game":2,"JPN":2,"Opponent":4,"Opponent name":"BRA","Period":2.0,"Player":"MAGARIYAMA S","Score":"4 - 2","Seconds":437,"Team":"JPN","Time":"7:17","Result":"Saved","Goal":0},{"Action":"Action shot","Cap":3.0,"Game":2,"JPN":2,"Opponent":4,"Opponent name":"BRA","Period":2.0,"Player":"ZABLITH M","Score":"4 - 2","Seconds":383,"Team":"BRA","Time":"6:23","Result":"Missed","Goal":0},{"Action":"5m shot","Cap":4.0,"Game":2,"JPN":2,"Opponent":4,"Opponent name":"BRA","Period":2.0,"Player":"MAGARIYAMA S","Score":"4 - 2","Seconds":376,"Team":"JPN","Time":"6:16","Result":"Missed","Goal":0},{"Action":"Action shot","Cap":2.0,"Game":2,"JPN":2,"Opponent":4,"Opponent name":"BRA","Period":2.0,"Player":"SAKANOUE C","Score":"4 - 2","Seconds":299,"Team":"JPN","Time":"4:59","Result":"Saved","Goal":0},{"Action":"5m shot","Cap":6.0,"Game":2,"JPN":2,"Opponent":5,"Opponent name":"BRA","Period":2.0,"Player":"CHIAPPINI I","Score":"5 - 2","Seconds":277,"Team":"BRA","Time":"4:37","Result":"Goal","Goal":1},{"Action":"5m shot","Cap":12.0,"Game":2,"JPN":2,"Opponent":5,"Opponent name":"BRA","Period":2.0,"Player":"SUZUKI K","Score":"5 - 2","Seconds":255,"Team":"JPN","Time":"4:15","Result":"Saved","Goal":0},{"Action":"Action shot","Cap":9.0,"Game":2,"JPN":2,"Opponent":5,"Opponent name":"BRA","Period":2.0,"Player":"HOSOYA K","Score":"5 - 2","Seconds":211,"Team":"JPN","Time":"3:31","Result":"Saved","Goal":0},{"Action":"Extra player shot","Cap":9.0,"Game":2,"JPN":2,"Opponent":6,"Opponent name":"BRA","Period":2.0,"Player":"DIAS M","Score":"6 - 2","Seconds":186,"Team":"BRA","Time":"3:06","Result":"Goal","Goal":1},{"Action":"Action shot","Cap":4.0,"Game":2,"JPN":2,"Opponent":6,"Opponent name":"BRA","Period":2.0,"Player":"MAGARIYAMA S","Score":"6 - 2","Seconds":154,"Team":"JPN","Time":"2:34","Result":"Saved","Goal":0},{"Action":"Action shot","Cap":4.0,"Game":2,"JPN":3,"Opponent":6,"Opponent name":"BRA","Period":2.0,"Player":"MAGARIYAMA S","Score":"6 - 3","Seconds":109,"Team":"JPN","Time":"1:49","Result":"Goal","Goal":1},{"Action":"Extra player shot","Cap":6.0,"Game":2,"JPN":3,"Opponent":6,"Opponent name":"BRA","Period":2.0,"Player":"CHIAPPINI I","Score":"6 - 3","Seconds":22,"Team":"BRA","Time":"0:22","Result":"Saved","Goal":0},{"Action":"5m shot","Cap":7.0,"Game":2,"JPN":3,"Opponent":6,"Opponent name":"BRA","Period":2.0,"Player":"NAKANO Y","Score":"6 - 3","Seconds":0,"Team":"JPN","Time":"0:00","Result":"Post","Goal":0},{"Action":"Counter attack","Cap":3.0,"Game":2,"JPN":4,"Opponent":6,"Opponent name":"BRA","Period":3.0,"Player":"KAZAMA Y","Score":"6 - 4","Seconds":349,"Team":"JPN","Time":"5:49","Result":"Goal","Goal":1},{"Action":"Extra player shot","Cap":5.0,"Game":2,"JPN":4,"Opponent":6,"Opponent name":"BRA","Period":3.0,"Player":"BARRONCAS L","Score":"6 - 4","Seconds":308,"Team":"BRA","Time":"5:08","Result":"Saved","Goal":0},{"Action":"Action shot","Cap":6.0,"Game":2,"JPN":4,"Opponent":7,"Opponent name":"BRA","Period":3.0,"Player":"CHIAPPINI I","Score":"7 - 4","Seconds":281,"Team":"BRA","Time":"4:41","Result":"Goal","Goal":1},{"Action":"Penalty shot","Cap":7.0,"Game":2,"JPN":5,"Opponent":7,"Opponent name":"BRA","Period":3.0,"Player":"NAKANO Y","Score":"7 - 5","Seconds":250,"Team":"JPN","Time":"4:10","Result":"Goal","Goal":1},{"Action":"Action shot","Cap":8.0,"Game":2,"JPN":5,"Opponent":8,"Opponent name":"BRA","Period":3.0,"Player":"CARVALHO L","Score":"8 - 5","Seconds":235,"Team":"BRA","Time":"3:55","Result":"Goal","Goal":1},{"Action":"5m shot","Cap":5.0,"Game":2,"JPN":5,"Opponent":8,"Opponent name":"BRA","Period":3.0,"Player":"NAKATA M","Score":"8 - 5","Seconds":212,"Team":"JPN","Time":"3:32","Result":"Missed","Goal":0},{"Action":"Extra player shot","Cap":9.0,"Game":2,"JPN":5,"Opponent":9,"Opponent name":"BRA","Period":3.0,"Player":"DIAS M","Score":"9 - 5","Seconds":183,"Team":"BRA","Time":"3:03","Result":"Goal","Goal":1},{"Action":"Extra player shot","Cap":10.0,"Game":2,"JPN":5,"Opponent":9,"Opponent name":"BRA","Period":3.0,"Player":"MORI T","Score":"9 - 5","Seconds":146,"Team":"JPN","Time":"2:26","Result":"Saved","Goal":0},{"Action":"Action shot","Cap":7.0,"Game":2,"JPN":6,"Opponent":9,"Opponent name":"BRA","Period":3.0,"Player":"NAKANO Y","Score":"9 - 6","Seconds":78,"Team":"JPN","Time":"1:18","Result":"Goal","Goal":1},{"Action":"Centre shot","Cap":12.0,"Game":2,"JPN":6,"Opponent":9,"Opponent name":"BRA","Period":3.0,"Player":"SUZUKI K","Score":"9 - 6","Seconds":42,"Team":"JPN","Time":"0:42","Result":"Saved","Goal":0},{"Action":"Action shot","Cap":6.0,"Game":2,"JPN":6,"Opponent":10,"Opponent name":"BRA","Period":3.0,"Player":"CHIAPPINI I","Score":"10 - 6","Seconds":37,"Team":"BRA","Time":"0:37","Result":"Goal","Goal":1},{"Action":"Action shot","Cap":3.0,"Game":2,"JPN":6,"Opponent":10,"Opponent name":"BRA","Period":3.0,"Player":"KAZAMA Y","Score":"10 - 6","Seconds":30,"Team":"JPN","Time":"0:30","Result":"Blocked","Goal":0},{"Action":"5m shot","Cap":7.0,"Game":2,"JPN":6,"Opponent":11,"Opponent name":"BRA","Period":4.0,"Player":"OLIVEIRA A","Score":"11 - 6","Seconds":459,"Team":"BRA","Time":"7:39","Result":"Goal","Goal":1},{"Action":"5m shot","Cap":7.0,"Game":2,"JPN":6,"Opponent":11,"Opponent name":"BRA","Period":4.0,"Player":"NAKANO Y","Score":"11 - 6","Seconds":436,"Team":"JPN","Time":"7:16","Result":"Post","Goal":0},{"Action":"5m shot","Cap":4.0,"Game":2,"JPN":6,"Opponent":11,"Opponent name":"BRA","Period":4.0,"Player":"MAGARIYAMA S","Score":"11 - 6","Seconds":360,"Team":"JPN","Time":"6:00","Result":"Post","Goal":0},{"Action":"5m shot","Cap":10.0,"Game":2,"JPN":6,"Opponent":11,"Opponent name":"BRA","Period":4.0,"Player":"MORI T","Score":"11 - 6","Seconds":311,"Team":"JPN","Time":"5:11","Result":"Blocked","Goal":0},{"Action":"Action shot","Cap":12.0,"Game":2,"JPN":7,"Opponent":11,"Opponent name":"BRA","Period":4.0,"Player":"SUZUKI K","Score":"11 - 7","Seconds":157,"Team":"JPN","Time":"2:37","Result":"Goal","Goal":1},{"Action":"5m shot","Cap":3.0,"Game":2,"JPN":8,"Opponent":11,"Opponent name":"BRA","Period":4.0,"Player":"KAZAMA Y","Score":"11 - 8","Seconds":43,"Team":"JPN","Time":"0:43","Result":"Goal","Goal":1},{"Action":"Action shot","Cap":6.0,"Game":3,"JPN":0,"Opponent":1,"Opponent name":"USA","Period":1.0,"Player":"STEFFENS M","Score":"0 - 1","Seconds":462,"Team":"USA","Time":"7:42","Result":"Goal","Goal":1},{"Action":"Action shot","Cap":6.0,"Game":3,"JPN":0,"Opponent":2,"Opponent name":"USA","Period":1.0,"Player":"STEFFENS M","Score":"0 - 2","Seconds":321,"Team":"USA","Time":"5:21","Result":"Goal","Goal":1},{"Action":"Action shot","Cap":8.0,"Game":3,"JPN":0,"Opponent":2,"Opponent name":"USA","Period":1.0,"Player":"HASHIGUCHI M","Score":"0 - 2","Seconds":265,"Team":"JPN","Time":"4:25","Result":"Saved","Goal":0},{"Action":"Extra player shot","Cap":4.0,"Game":3,"JPN":0,"Opponent":3,"Opponent name":"USA","Period":1.0,"Player":"FATTAL R","Score":"0 - 3","Seconds":143,"Team":"USA","Time":"2:23","Result":"Goal","Goal":1},{"Action":"Centre shot","Cap":12.0,"Game":3,"JPN":0,"Opponent":4,"Opponent name":"USA","Period":1.0,"Player":"CRAIG K","Score":"0 - 4","Seconds":61,"Team":"USA","Time":"1:01","Result":"Goal","Goal":1},{"Action":"Action shot","Cap":9.0,"Game":3,"JPN":0,"Opponent":4,"Opponent name":"USA","Period":1.0,"Player":"GROSSMAN A","Score":"0 - 4","Seconds":3,"Team":"USA","Time":"0:03","Result":"Saved","Goal":0},{"Action":"Action shot","Cap":11.0,"Game":3,"JPN":0,"Opponent":4,"Opponent name":"USA","Period":2.0,"Player":"FISCHER M","Score":"0 - 4","Seconds":464,"Team":"USA","Time":"7:44","Result":"Post","Goal":0},{"Action":"Action shot","Cap":2.0,"Game":3,"JPN":0,"Opponent":5,"Opponent name":"USA","Period":2.0,"Player":"MUSSELMAN M","Score":"0 - 5","Seconds":431,"Team":"USA","Time":"7:11","Result":"Goal","Goal":1},{"Action":"Action shot","Cap":10.0,"Game":3,"JPN":0,"Opponent":5,"Opponent name":"USA","Period":2.0,"Player":"MORI T","Score":"0 - 5","Seconds":333,"Team":"JPN","Time":"5:33","Result":"Saved","Goal":0},{"Action":"Action shot","Cap":11.0,"Game":3,"JPN":0,"Opponent":6,"Opponent name":"USA","Period":2.0,"Player":"FISCHER M","Score":"0 - 6","Seconds":316,"Team":"USA","Time":"5:16","Result":"Goal","Goal":1},{"Action":"Action shot","Cap":6.0,"Game":3,"JPN":0,"Opponent":7,"Opponent name":"USA","Period":2.0,"Player":"STEFFENS M","Score":"0 - 7","Seconds":291,"Team":"USA","Time":"4:51","Result":"Goal","Goal":1},{"Action":"Action shot","Cap":8.0,"Game":3,"JPN":0,"Opponent":7,"Opponent name":"USA","Period":2.0,"Player":"HASHIGUCHI M","Score":"0 - 7","Seconds":262,"Team":"JPN","Time":"4:22","Result":"Missed","Goal":0},{"Action":"Action shot","Cap":7.0,"Game":3,"JPN":0,"Opponent":7,"Opponent name":"USA","Period":2.0,"Player":"NAKANO Y","Score":"0 - 7","Seconds":239,"Team":"JPN","Time":"3:59","Result":"Saved","Goal":0},{"Action":"Action shot","Cap":12.0,"Game":3,"JPN":0,"Opponent":8,"Opponent name":"USA","Period":2.0,"Player":"CRAIG K","Score":"0 - 8","Seconds":191,"Team":"USA","Time":"3:11","Result":"Goal","Goal":1},{"Action":"Action shot","Cap":7.0,"Game":3,"JPN":0,"Opponent":8,"Opponent name":"USA","Period":2.0,"Player":"NAKANO Y","Score":"0 - 8","Seconds":10,"Team":"JPN","Time":"0:10","Result":"Blocked","Goal":0},{"Action":"Centre shot","Cap":2.0,"Game":3,"JPN":0,"Opponent":8,"Opponent name":"USA","Period":2.0,"Player":"MUSSELMAN M","Score":"0 - 8","Seconds":4,"Team":"USA","Time":"0:04","Result":"Post","Goal":0},{"Action":"Action shot","Cap":9.0,"Game":3,"JPN":0,"Opponent":8,"Opponent name":"USA","Period":3.0,"Player":"HOSOYA K","Score":"0 - 8","Seconds":446,"Team":"JPN","Time":"7:26","Result":"Missed","Goal":0},{"Action":"Extra player shot","Cap":8.0,"Game":3,"JPN":0,"Opponent":9,"Opponent name":"USA","Period":3.0,"Player":"NEUSHUL K","Score":"0 - 9","Seconds":416,"Team":"USA","Time":"6:56","Result":"Goal","Goal":1},{"Action":"Counter attack","Cap":7.0,"Game":3,"JPN":0,"Opponent":10,"Opponent name":"USA","Period":3.0,"Player":"MATHEWSON C","Score":"0 - 10","Seconds":384,"Team":"USA","Time":"6:24","Result":"Goal","Goal":1},{"Action":"Counter attack","Cap":6.0,"Game":3,"JPN":0,"Opponent":11,"Opponent name":"USA","Period":3.0,"Player":"STEFFENS M","Score":"0 - 11","Seconds":352,"Team":"USA","Time":"5:52","Result":"Goal","Goal":1},{"Action":"Action shot","Cap":12.0,"Game":3,"JPN":0,"Opponent":11,"Opponent name":"USA","Period":3.0,"Player":"CRAIG K","Score":"0 - 11","Seconds":263,"Team":"USA","Time":"4:23","Result":"Missed","Goal":0},{"Action":"Action shot","Cap":12.0,"Game":3,"JPN":0,"Opponent":12,"Opponent name":"USA","Period":3.0,"Player":"CRAIG K","Score":"0 - 12","Seconds":196,"Team":"USA","Time":"3:16","Result":"Goal","Goal":1},{"Action":"Counter attack","Cap":9.0,"Game":3,"JPN":0,"Opponent":13,"Opponent name":"USA","Period":3.0,"Player":"GROSSMAN A","Score":"0 - 13","Seconds":157,"Team":"USA","Time":"2:37","Result":"Goal","Goal":1},{"Action":"Extra player shot","Cap":2.0,"Game":3,"JPN":0,"Opponent":13,"Opponent name":"USA","Period":3.0,"Player":"SAKANOUE C","Score":"0 - 13","Seconds":120,"Team":"JPN","Time":"2:00","Result":"Saved","Goal":0},{"Action":"Action shot","Cap":9.0,"Game":3,"JPN":0,"Opponent":14,"Opponent name":"USA","Period":3.0,"Player":"GROSSMAN A","Score":"0 - 14","Seconds":104,"Team":"USA","Time":"1:44","Result":"Goal","Goal":1},{"Action":"Action shot","Cap":7.0,"Game":3,"JPN":1,"Opponent":14,"Opponent name":"USA","Period":3.0,"Player":"NAKANO Y","Score":"1 - 14","Seconds":74,"Team":"JPN","Time":"1:14","Result":"Goal","Goal":1},{"Action":"Extra player shot","Cap":10.0,"Game":3,"JPN":1,"Opponent":14,"Opponent name":"USA","Period":3.0,"Player":"GILCHRIST K","Score":"1 - 14","Seconds":32,"Team":"USA","Time":"0:32","Result":"Missed","Goal":0},{"Action":"5m shot","Cap":6.0,"Game":3,"JPN":1,"Opponent":14,"Opponent name":"USA","Period":3.0,"Player":"TAKAHASHI A","Score":"1 - 14","Seconds":13,"Team":"JPN","Time":"0:13","Result":"Saved","Goal":0},{"Action":"Centre shot","Cap":6.0,"Game":3,"JPN":1,"Opponent":14,"Opponent name":"USA","Period":4.0,"Player":"STEFFENS M","Score":"1 - 14","Seconds":362,"Team":"USA","Time":"6:02","Result":"Post","Goal":0},{"Action":"Action shot","Cap":7.0,"Game":3,"JPN":1,"Opponent":14,"Opponent name":"USA","Period":4.0,"Player":"NAKANO Y","Score":"1 - 14","Seconds":325,"Team":"JPN","Time":"5:25","Result":"Blocked","Goal":0},{"Action":"Counter attack","Cap":7.0,"Game":3,"JPN":2,"Opponent":14,"Opponent name":"USA","Period":4.0,"Player":"NAKANO Y","Score":"2 - 14","Seconds":286,"Team":"JPN","Time":"4:46","Result":"Goal","Goal":1},{"Action":"Action shot","Cap":9.0,"Game":3,"JPN":2,"Opponent":15,"Opponent name":"USA","Period":4.0,"Player":"GROSSMAN A","Score":"2 - 15","Seconds":276,"Team":"USA","Time":"4:36","Result":"Goal","Goal":1},{"Action":"Action shot","Cap":11.0,"Game":3,"JPN":2,"Opponent":16,"Opponent name":"USA","Period":4.0,"Player":"FISCHER M","Score":"2 - 16","Seconds":231,"Team":"USA","Time":"3:51","Result":"Goal","Goal":1},{"Action":"Action shot","Cap":2.0,"Game":3,"JPN":2,"Opponent":17,"Opponent name":"USA","Period":4.0,"Player":"MUSSELMAN M","Score":"2 - 17","Seconds":49,"Team":"USA","Time":"0:49","Result":"Goal","Goal":1},{"Action":"Action shot","Cap":3.0,"Game":3,"JPN":2,"Opponent":17,"Opponent name":"USA","Period":4.0,"Player":"SEIDEMANN M","Score":"2 - 17","Seconds":1,"Team":"USA","Time":"0:01","Result":"Missed","Goal":0},{"Action":"Extra player shot","Cap":5.0,"Game":4,"JPN":1,"Opponent":0,"Opponent name":"FRA","Period":1.0,"Player":"NAKATA M","Score":"1 - 0","Seconds":403,"Team":"JPN","Time":"6:43","Result":"Goal","Goal":1},{"Action":"Action shot","Cap":6.0,"Game":4,"JPN":2,"Opponent":0,"Opponent name":"FRA","Period":1.0,"Player":"TAKAHASHI A","Score":"2 - 0","Seconds":355,"Team":"JPN","Time":"5:55","Result":"Goal","Goal":1},{"Action":"5m shot","Cap":7.0,"Game":4,"JPN":2,"Opponent":0,"Opponent name":"FRA","Period":1.0,"Player":"NAKANO Y","Score":"2 - 0","Seconds":310,"Team":"JPN","Time":"5:10","Result":"Saved","Goal":0},{"Action":"Action shot","Cap":11.0,"Game":4,"JPN":2,"Opponent":0,"Opponent name":"FRA","Period":1.0,"Player":"TOKUMOTO M","Score":"2 - 0","Seconds":248,"Team":"JPN","Time":"4:08","Result":"Saved","Goal":0},{"Action":"Centre shot","Cap":3.0,"Game":4,"JPN":2,"Opponent":0,"Opponent name":"FRA","Period":1.0,"Player":"BACHELIER L","Score":"2 - 0","Seconds":224,"Team":"FRA","Time":"3:44","Result":"Post","Goal":0},{"Action":"Centre shot","Cap":7.0,"Game":4,"JPN":3,"Opponent":0,"Opponent name":"FRA","Period":1.0,"Player":"NAKANO Y","Score":"3 - 0","Seconds":200,"Team":"JPN","Time":"3:20","Result":"Goal","Goal":1},{"Action":"5m shot","Cap":2.0,"Game":4,"JPN":3,"Opponent":0,"Opponent name":"FRA","Period":1.0,"Player":"MILLOT E","Score":"3 - 0","Seconds":148,"Team":"FRA","Time":"2:28","Result":"Missed","Goal":0},{"Action":"Extra player shot","Cap":5.0,"Game":4,"JPN":3,"Opponent":1,"Opponent name":"FRA","Period":1.0,"Player":"GUILLET L","Score":"3 - 1","Seconds":105,"Team":"FRA","Time":"1:45","Result":"Goal","Goal":1},{"Action":"Penalty shot","Cap":5.0,"Game":4,"JPN":3,"Opponent":2,"Opponent name":"FRA","Period":1.0,"Player":"GUILLET L","Score":"3 - 2","Seconds":73,"Team":"FRA","Time":"1:13","Result":"Goal","Goal":1},{"Action":"5m shot","Cap":4.0,"Game":4,"JPN":3,"Opponent":2,"Opponent name":"FRA","Period":1.0,"Player":"MAGARIYAMA S","Score":"3 - 2","Seconds":46,"Team":"JPN","Time":"0:46","Result":"Saved","Goal":0},{"Action":"Action shot","Cap":2.0,"Game":4,"JPN":3,"Opponent":2,"Opponent name":"FRA","Period":1.0,"Player":"SAKANOUE C","Score":"3 - 2","Seconds":0,"Team":"JPN","Time":"0:00","Result":"Saved","Goal":0},{"Action":"5m shot","Cap":8.0,"Game":4,"JPN":3,"Opponent":2,"Opponent name":"FRA","Period":2.0,"Player":"HASHIGUCHI M","Score":"3 - 2","Seconds":429,"Team":"JPN","Time":"7:09","Result":"Missed","Goal":0},{"Action":"Action shot","Cap":6.0,"Game":4,"JPN":3,"Opponent":3,"Opponent name":"FRA","Period":2.0,"Player":"MAHIEU G","Score":"3 - 3","Seconds":356,"Team":"FRA","Time":"5:56","Result":"Goal","Goal":1},{"Action":"Action shot","Cap":5.0,"Game":4,"JPN":3,"Opponent":4,"Opponent name":"FRA","Period":2.0,"Player":"GUILLET L","Score":"3 - 4","Seconds":313,"Team":"FRA","Time":"5:13","Result":"Goal","Goal":1},{"Action":"Extra player shot","Cap":2.0,"Game":4,"JPN":3,"Opponent":4,"Opponent name":"FRA","Period":2.0,"Player":"SAKANOUE C","Score":"3 - 4","Seconds":295,"Team":"JPN","Time":"4:55","Result":"Saved","Goal":0},{"Action":"Penalty shot","Cap":5.0,"Game":4,"JPN":3,"Opponent":5,"Opponent name":"FRA","Period":2.0,"Player":"GUILLET L","Score":"3 - 5","Seconds":273,"Team":"FRA","Time":"4:33","Result":"Goal","Goal":1},{"Action":"Extra player shot","Cap":12.0,"Game":4,"JPN":4,"Opponent":5,"Opponent name":"FRA","Period":2.0,"Player":"SUZUKI K","Score":"4 - 5","Seconds":239,"Team":"JPN","Time":"3:59","Result":"Goal","Goal":1},{"Action":"5m shot","Cap":10.0,"Game":4,"JPN":4,"Opponent":5,"Opponent name":"FRA","Period":2.0,"Player":"MORI T","Score":"4 - 5","Seconds":96,"Team":"JPN","Time":"1:36","Result":"Saved","Goal":0},{"Action":"Action shot","Cap":5.0,"Game":4,"JPN":4,"Opponent":5,"Opponent name":"FRA","Period":2.0,"Player":"NAKATA M","Score":"4 - 5","Seconds":57,"Team":"JPN","Time":"0:57","Result":"Post","Goal":0},{"Action":"5m shot","Cap":8.0,"Game":4,"JPN":4,"Opponent":5,"Opponent name":"FRA","Period":2.0,"Player":"HASHIGUCHI M","Score":"4 - 5","Seconds":16,"Team":"JPN","Time":"0:16","Result":"Post","Goal":0},{"Action":"Action shot","Cap":3.0,"Game":4,"JPN":4,"Opponent":5,"Opponent name":"FRA","Period":4.0,"Player":"KAZAMA Y","Score":"4 - 5","Seconds":73,"Team":"JPN","Time":"1:13","Result":"Saved","Goal":0},{"Action":"Action shot","Cap":2.0,"Game":4,"JPN":4,"Opponent":5,"Opponent name":"FRA","Period":4.0,"Player":"SAKANOUE C","Score":"4 - 5","Seconds":21,"Team":"JPN","Time":"0:21","Result":"Blocked","Goal":0},{"Action":"Action shot","Cap":5.0,"Game":4,"JPN":4,"Opponent":6,"Opponent name":"FRA","Period":2.0,"Player":"GUILLET L","Score":"4 - 6","Seconds":3,"Team":"FRA","Time":"0:03","Result":"Goal","Goal":1},{"Action":"5m shot","Cap":11.0,"Game":4,"JPN":4,"Opponent":6,"Opponent name":"FRA","Period":2.0,"Player":"TOKUMOTO M","Score":"4 - 6","Seconds":0,"Team":"JPN","Time":"0:00","Result":"Post","Goal":0},{"Action":"Counter attack","Cap":12.0,"Game":4,"JPN":4,"Opponent":6,"Opponent name":"FRA","Period":3.0,"Player":"SUZUKI K","Score":"4 - 6","Seconds":445,"Team":"JPN","Time":"7:25","Result":"Post","Goal":0},{"Action":"Extra player shot","Cap":8.0,"Game":4,"JPN":4,"Opponent":6,"Opponent name":"FRA","Period":3.0,"Player":"TARDY M","Score":"4 - 6","Seconds":396,"Team":"FRA","Time":"6:36","Result":"Post","Goal":0},{"Action":"Centre shot","Cap":2.0,"Game":4,"JPN":4,"Opponent":6,"Opponent name":"FRA","Period":3.0,"Player":"MILLOT E","Score":"4 - 6","Seconds":274,"Team":"FRA","Time":"4:34","Result":"Missed","Goal":0},{"Action":"Action shot","Cap":9.0,"Game":4,"JPN":4,"Opponent":6,"Opponent name":"FRA","Period":3.0,"Player":"HOSOYA K","Score":"4 - 6","Seconds":261,"Team":"JPN","Time":"4:21","Result":"Missed","Goal":0},{"Action":"5m shot","Cap":2.0,"Game":4,"JPN":4,"Opponent":7,"Opponent name":"FRA","Period":3.0,"Player":"MILLOT E","Score":"4 - 7","Seconds":125,"Team":"FRA","Time":"2:05","Result":"Goal","Goal":1},{"Action":"Action shot","Cap":4.0,"Game":4,"JPN":4,"Opponent":7,"Opponent name":"FRA","Period":3.0,"Player":"MAGARIYAMA S","Score":"4 - 7","Seconds":88,"Team":"JPN","Time":"1:28","Result":"Blocked","Goal":0},{"Action":"Action shot","Cap":9.0,"Game":4,"JPN":4,"Opponent":7,"Opponent name":"FRA","Period":3.0,"Player":"HOSOYA K","Score":"4 - 7","Seconds":55,"Team":"JPN","Time":"0:55","Result":"Saved","Goal":0},{"Action":"Extra player shot","Cap":9.0,"Game":4,"JPN":5,"Opponent":7,"Opponent name":"FRA","Period":3.0,"Player":"HOSOYA K","Score":"5 - 7","Seconds":10,"Team":"JPN","Time":"0:10","Result":"Goal","Goal":1},{"Action":"5m shot","Cap":5.0,"Game":4,"JPN":5,"Opponent":7,"Opponent name":"FRA","Period":3.0,"Player":"GUILLET L","Score":"5 - 7","Seconds":0,"Team":"FRA","Time":"0:00","Result":"Missed","Goal":0},{"Action":"5m shot","Cap":4.0,"Game":4,"JPN":5,"Opponent":7,"Opponent name":"FRA","Period":4.0,"Player":"MAGARIYAMA S","Score":"5 - 7","Seconds":451,"Team":"JPN","Time":"7:31","Result":"Saved","Goal":0},{"Action":"Action shot","Cap":8.0,"Game":4,"JPN":5,"Opponent":8,"Opponent name":"FRA","Period":4.0,"Player":"TARDY M","Score":"5 - 8","Seconds":404,"Team":"FRA","Time":"6:44","Result":"Goal","Goal":1},{"Action":"Action shot","Cap":7.0,"Game":4,"JPN":6,"Opponent":8,"Opponent name":"FRA","Period":4.0,"Player":"NAKANO Y","Score":"6 - 8","Seconds":343,"Team":"JPN","Time":"5:43","Result":"Goal","Goal":1},{"Action":"Action shot","Cap":7.0,"Game":4,"JPN":6,"Opponent":8,"Opponent name":"FRA","Period":4.0,"Player":"NAKANO Y","Score":"6 - 8","Seconds":296,"Team":"JPN","Time":"4:56","Result":"Post","Goal":0},{"Action":"Extra player shot","Cap":7.0,"Game":4,"JPN":6,"Opponent":8,"Opponent name":"FRA","Period":4.0,"Player":"NAKANO Y","Score":"6 - 8","Seconds":230,"Team":"JPN","Time":"3:50","Result":"Post","Goal":0},{"Action":"Centre shot","Cap":6.0,"Game":4,"JPN":6,"Opponent":8,"Opponent name":"FRA","Period":4.0,"Player":"MAHIEU G","Score":"6 - 8","Seconds":191,"Team":"FRA","Time":"3:11","Result":"Saved","Goal":0},{"Action":"Action shot","Cap":9.0,"Game":4,"JPN":6,"Opponent":8,"Opponent name":"FRA","Period":4.0,"Player":"HOSOYA K","Score":"6 - 8","Seconds":175,"Team":"JPN","Time":"2:55","Result":"Blocked","Goal":0},{"Action":"Extra player shot","Cap":3.0,"Game":4,"JPN":6,"Opponent":8,"Opponent name":"FRA","Period":4.0,"Player":"KAZAMA Y","Score":"6 - 8","Seconds":125,"Team":"JPN","Time":"2:05","Result":"Saved","Goal":0},{"Action":"5m shot","Cap":5.0,"Game":4,"JPN":6,"Opponent":8,"Opponent name":"FRA","Period":4.0,"Player":"GUILLET L","Score":"6 - 8","Seconds":103,"Team":"FRA","Time":"1:43","Result":"Missed","Goal":0},{"Action":"Counter attack","Cap":3.0,"Game":4,"JPN":6,"Opponent":8,"Opponent name":"FRA","Period":4.0,"Player":"KAZAMA Y","Score":"6 - 8","Seconds":91,"Team":"JPN","Time":"1:31","Result":"Post","Goal":0},{"Action":"Penalty shot","Cap":3.0,"Game":4,"JPN":6,"Opponent":9,"Opponent name":"FRA","Period":4.0,"Player":"BACHELIER L","Score":"6 - 9","Seconds":4,"Team":"FRA","Time":"0:04","Result":"Goal","Goal":1},{"Action":"5m shot","Cap":4.0,"Game":4,"JPN":6,"Opponent":9,"Opponent name":"FRA","Period":4.0,"Player":"MAGARIYAMA S","Score":"6 - 9","Seconds":0,"Team":"JPN","Time":"0:00","Result":"Saved","Goal":0},{"Action":"Action shot","Cap":4.0,"Game":5,"JPN":0,"Opponent":0,"Opponent name":"RSA","Period":1.0,"Player":"MAGARIYAMA S","Score":"0 - 0","Seconds":447,"Team":"JPN","Time":"7:27","Result":"Missed","Goal":0},{"Action":"Extra player shot","Cap":6.0,"Game":5,"JPN":1,"Opponent":0,"Opponent name":"RSA","Period":1.0,"Player":"TAKAHASHI A","Score":"0 - 1","Seconds":395,"Team":"JPN","Time":"6:35","Result":"Goal","Goal":1},{"Action":"Action shot","Cap":4.0,"Game":5,"JPN":1,"Opponent":0,"Opponent name":"RSA","Period":1.0,"Player":"VERSFELD R","Score":"0 - 1","Seconds":310,"Team":"RSA","Time":"5:10","Result":"Saved","Goal":0},{"Action":"Action shot","Cap":5.0,"Game":5,"JPN":1,"Opponent":0,"Opponent name":"RSA","Period":1.0,"Player":"NAKATA M","Score":"0 - 1","Seconds":303,"Team":"JPN","Time":"5:03","Result":"Saved","Goal":0},{"Action":"Action shot","Cap":4.0,"Game":5,"JPN":1,"Opponent":0,"Opponent name":"RSA","Period":1.0,"Player":"VERSFELD R","Score":"0 - 1","Seconds":257,"Team":"RSA","Time":"4:17","Result":"Saved","Goal":0},{"Action":"5m shot","Cap":10.0,"Game":5,"JPN":1,"Opponent":0,"Opponent name":"RSA","Period":1.0,"Player":"MORI T","Score":"0 - 1","Seconds":235,"Team":"JPN","Time":"3:55","Result":"Saved","Goal":0},{"Action":"Counter attack","Cap":8.0,"Game":5,"JPN":2,"Opponent":0,"Opponent name":"RSA","Period":1.0,"Player":"HASHIGUCHI M","Score":"0 - 2","Seconds":205,"Team":"JPN","Time":"3:25","Result":"Goal","Goal":1},{"Action":"5m shot","Cap":12.0,"Game":5,"JPN":2,"Opponent":0,"Opponent name":"RSA","Period":1.0,"Player":"WHITE K","Score":"0 - 2","Seconds":125,"Team":"RSA","Time":"2:05","Result":"Blocked","Goal":0},{"Action":"5m shot","Cap":7.0,"Game":5,"JPN":2,"Opponent":0,"Opponent name":"RSA","Period":1.0,"Player":"NAKANO Y","Score":"0 - 2","Seconds":105,"Team":"JPN","Time":"1:45","Result":"Saved","Goal":0},{"Action":"Action shot","Cap":8.0,"Game":5,"JPN":2,"Opponent":0,"Opponent name":"RSA","Period":1.0,"Player":"HASHIGUCHI M","Score":"0 - 2","Seconds":64,"Team":"JPN","Time":"1:04","Result":"Saved","Goal":0},{"Action":"Action shot","Cap":3.0,"Game":5,"JPN":2,"Opponent":0,"Opponent name":"RSA","Period":1.0,"Player":"PALEY K","Score":"0 - 2","Seconds":32,"Team":"RSA","Time":"0:32","Result":"Saved","Goal":0},{"Action":"Action shot","Cap":6.0,"Game":5,"JPN":2,"Opponent":0,"Opponent name":"RSA","Period":2.0,"Player":"TAKAHASHI A","Score":"0 - 2","Seconds":424,"Team":"JPN","Time":"7:04","Result":"Missed","Goal":0},{"Action":"Counter attack","Cap":4.0,"Game":5,"JPN":2,"Opponent":0,"Opponent name":"RSA","Period":2.0,"Player":"MAGARIYAMA S","Score":"0 - 2","Seconds":389,"Team":"JPN","Time":"6:29","Result":"Post","Goal":0},{"Action":"Counter attack","Cap":8.0,"Game":5,"JPN":2,"Opponent":0,"Opponent name":"RSA","Period":2.0,"Player":"HASHIGUCHI M","Score":"0 - 2","Seconds":358,"Team":"JPN","Time":"5:58","Result":"Saved","Goal":0},{"Action":"Action shot","Cap":12.0,"Game":5,"JPN":2,"Opponent":0,"Opponent name":"RSA","Period":2.0,"Player":"WHITE K","Score":"0 - 2","Seconds":318,"Team":"RSA","Time":"5:18","Result":"Post","Goal":0},{"Action":"Action shot","Cap":7.0,"Game":5,"JPN":3,"Opponent":0,"Opponent name":"RSA","Period":2.0,"Player":"NAKANO Y","Score":"0 - 3","Seconds":296,"Team":"JPN","Time":"4:56","Result":"Goal","Goal":1},{"Action":"Action shot","Cap":7.0,"Game":5,"JPN":3,"Opponent":0,"Opponent name":"RSA","Period":2.0,"Player":"KAY K","Score":"0 - 3","Seconds":229,"Team":"RSA","Time":"3:49","Result":"Missed","Goal":0},{"Action":"Action shot","Cap":4.0,"Game":5,"JPN":3,"Opponent":0,"Opponent name":"RSA","Period":2.0,"Player":"VERSFELD R","Score":"0 - 3","Seconds":178,"Team":"RSA","Time":"2:58","Result":"Missed","Goal":0},{"Action":"5m shot","Cap":3.0,"Game":5,"JPN":3,"Opponent":0,"Opponent name":"RSA","Period":2.0,"Player":"KAZAMA Y","Score":"0 - 3","Seconds":165,"Team":"JPN","Time":"2:45","Result":"Saved","Goal":0},{"Action":"Action shot","Cap":8.0,"Game":5,"JPN":3,"Opponent":0,"Opponent name":"RSA","Period":2.0,"Player":"HASHIGUCHI M","Score":"0 - 3","Seconds":119,"Team":"JPN","Time":"1:59","Result":"Saved","Goal":0},{"Action":"Extra player shot","Cap":7.0,"Game":5,"JPN":3,"Opponent":0,"Opponent name":"RSA","Period":4.0,"Player":"KAY K","Score":"0 - 3","Seconds":171,"Team":"RSA","Time":"2:51","Result":"Saved","Goal":0},{"Action":"Counter attack","Cap":12.0,"Game":5,"JPN":15,"Opponent":6,"Opponent name":"RSA","Period":4.0,"Player":"WHITE K","Score":"6 - 15","Seconds":145,"Team":"RSA","Time":"2:25","Result":"Goal","Goal":1},{"Action":"Action shot","Cap":10.0,"Game":5,"JPN":15,"Opponent":6,"Opponent name":"RSA","Period":2.0,"Player":"MORI T","Score":"6 - 15","Seconds":94,"Team":"JPN","Time":"1:34","Result":"Saved","Goal":0},{"Action":"Counter attack","Cap":7.0,"Game":5,"JPN":4,"Opponent":0,"Opponent name":"RSA","Period":2.0,"Player":"NAKANO Y","Score":"0 - 4","Seconds":78,"Team":"JPN","Time":"1:18","Result":"Goal","Goal":1},{"Action":"Action shot","Cap":7.0,"Game":5,"JPN":4,"Opponent":0,"Opponent name":"RSA","Period":2.0,"Player":"NAKANO Y","Score":"0 - 4","Seconds":47,"Team":"JPN","Time":"0:47","Result":"Missed","Goal":0},{"Action":"Action shot","Cap":10.0,"Game":5,"JPN":4,"Opponent":0,"Opponent name":"RSA","Period":2.0,"Player":"MORI T","Score":"0 - 4","Seconds":14,"Team":"JPN","Time":"0:14","Result":"Saved","Goal":0},{"Action":"5m shot","Cap":12.0,"Game":5,"JPN":4,"Opponent":0,"Opponent name":"RSA","Period":2.0,"Player":"WHITE K","Score":"0 - 4","Seconds":0,"Team":"RSA","Time":"0:00","Result":"Saved","Goal":0},{"Action":"Action shot","Cap":4.0,"Game":5,"JPN":4,"Opponent":1,"Opponent name":"RSA","Period":3.0,"Player":"VERSFELD R","Score":"1 - 4","Seconds":455,"Team":"RSA","Time":"7:35","Result":"Goal","Goal":1},{"Action":"5m shot","Cap":11.0,"Game":5,"JPN":4,"Opponent":1,"Opponent name":"RSA","Period":3.0,"Player":"TOKUMOTO M","Score":"1 - 4","Seconds":429,"Team":"JPN","Time":"7:09","Result":"Missed","Goal":0},{"Action":"Counter attack","Cap":11.0,"Game":5,"JPN":5,"Opponent":1,"Opponent name":"RSA","Period":3.0,"Player":"TOKUMOTO M","Score":"1 - 5","Seconds":413,"Team":"JPN","Time":"6:53","Result":"Goal","Goal":1},{"Action":"Counter attack","Cap":2.0,"Game":5,"JPN":6,"Opponent":1,"Opponent name":"RSA","Period":3.0,"Player":"SAKANOUE C","Score":"1 - 6","Seconds":386,"Team":"JPN","Time":"6:26","Result":"Goal","Goal":1},{"Action":"Action shot","Cap":7.0,"Game":5,"JPN":6,"Opponent":1,"Opponent name":"RSA","Period":3.0,"Player":"KAY K","Score":"1 - 6","Seconds":365,"Team":"RSA","Time":"6:05","Result":"Saved","Goal":0},{"Action":"Action shot","Cap":11.0,"Game":5,"JPN":6,"Opponent":2,"Opponent name":"RSA","Period":3.0,"Player":"O'HANLON D","Score":"2 - 6","Seconds":341,"Team":"RSA","Time":"5:41","Result":"Goal","Goal":1},{"Action":"Counter attack","Cap":5.0,"Game":5,"JPN":6,"Opponent":2,"Opponent name":"RSA","Period":3.0,"Player":"NAKATA M","Score":"2 - 6","Seconds":303,"Team":"JPN","Time":"5:03","Result":"Saved","Goal":0},{"Action":"Counter attack","Cap":8.0,"Game":5,"JPN":7,"Opponent":2,"Opponent name":"RSA","Period":3.0,"Player":"HASHIGUCHI M","Score":"2 - 7","Seconds":298,"Team":"JPN","Time":"4:58","Result":"Goal","Goal":1},{"Action":"Counter attack","Cap":7.0,"Game":5,"JPN":8,"Opponent":2,"Opponent name":"RSA","Period":3.0,"Player":"NAKANO Y","Score":"2 - 8","Seconds":264,"Team":"JPN","Time":"4:24","Result":"Goal","Goal":1},{"Action":"Counter attack","Cap":2.0,"Game":5,"JPN":9,"Opponent":2,"Opponent name":"RSA","Period":3.0,"Player":"SAKANOUE C","Score":"2 - 9","Seconds":237,"Team":"JPN","Time":"3:57","Result":"Goal","Goal":1},{"Action":"Action shot","Cap":10.0,"Game":5,"JPN":10,"Opponent":2,"Opponent name":"RSA","Period":3.0,"Player":"MORI T","Score":"2 - 10","Seconds":186,"Team":"JPN","Time":"3:06","Result":"Goal","Goal":1},{"Action":"Centre shot","Cap":8.0,"Game":5,"JPN":10,"Opponent":2,"Opponent name":"RSA","Period":3.0,"Player":"HASHIGUCHI M","Score":"2 - 10","Seconds":136,"Team":"JPN","Time":"2:16","Result":"Saved","Goal":0},{"Action":"Action shot","Cap":7.0,"Game":5,"JPN":11,"Opponent":2,"Opponent name":"RSA","Period":3.0,"Player":"NAKANO Y","Score":"2 - 11","Seconds":124,"Team":"JPN","Time":"2:04","Result":"Goal","Goal":1},{"Action":"Action shot","Cap":3.0,"Game":5,"JPN":11,"Opponent":2,"Opponent name":"RSA","Period":3.0,"Player":"PALEY K","Score":"2 - 11","Seconds":98,"Team":"RSA","Time":"1:38","Result":"Saved","Goal":0},{"Action":"5m shot","Cap":5.0,"Game":5,"JPN":12,"Opponent":2,"Opponent name":"RSA","Period":3.0,"Player":"NAKATA M","Score":"2 - 12","Seconds":78,"Team":"JPN","Time":"1:18","Result":"Goal","Goal":1},{"Action":"Centre shot","Cap":7.0,"Game":5,"JPN":12,"Opponent":2,"Opponent name":"RSA","Period":3.0,"Player":"KAY K","Score":"2 - 12","Seconds":61,"Team":"RSA","Time":"1:01","Result":"Post","Goal":0},{"Action":"Centre shot","Cap":7.0,"Game":5,"JPN":12,"Opponent":3,"Opponent name":"RSA","Period":3.0,"Player":"KAY K","Score":"3 - 12","Seconds":55,"Team":"RSA","Time":"0:55","Result":"Goal","Goal":1},{"Action":"5m shot","Cap":12.0,"Game":5,"JPN":12,"Opponent":3,"Opponent name":"RSA","Period":3.0,"Player":"SUZUKI K","Score":"3 - 12","Seconds":32,"Team":"JPN","Time":"0:32","Result":"Saved","Goal":0},{"Action":"Extra player shot","Cap":7.0,"Game":5,"JPN":12,"Opponent":3,"Opponent name":"RSA","Period":3.0,"Player":"KAY K","Score":"3 - 12","Seconds":1,"Team":"RSA","Time":"0:01","Result":"Missed","Goal":0},{"Action":"5m shot","Cap":10.0,"Game":5,"JPN":13,"Opponent":3,"Opponent name":"RSA","Period":4.0,"Player":"MORI T","Score":"3 - 13","Seconds":422,"Team":"JPN","Time":"7:02","Result":"Goal","Goal":1},{"Action":"Centre shot","Cap":7.0,"Game":5,"JPN":13,"Opponent":3,"Opponent name":"RSA","Period":4.0,"Player":"KAY K","Score":"3 - 13","Seconds":406,"Team":"RSA","Time":"6:46","Result":"Saved","Goal":0},{"Action":"Extra player shot","Cap":12.0,"Game":5,"JPN":13,"Opponent":4,"Opponent name":"RSA","Period":4.0,"Player":"WHITE K","Score":"4 - 13","Seconds":358,"Team":"RSA","Time":"5:58","Result":"Goal","Goal":1},{"Action":"5m shot","Cap":4.0,"Game":5,"JPN":13,"Opponent":4,"Opponent name":"RSA","Period":4.0,"Player":"MAGARIYAMA S","Score":"4 - 13","Seconds":311,"Team":"JPN","Time":"5:11","Result":"Post","Goal":0},{"Action":"Action shot","Cap":6.0,"Game":5,"JPN":13,"Opponent":5,"Opponent name":"RSA","Period":4.0,"Player":"HALLENDORFF A","Score":"5 - 13","Seconds":289,"Team":"RSA","Time":"4:49","Result":"Goal","Goal":1},{"Action":"Action shot","Cap":9.0,"Game":5,"JPN":14,"Opponent":5,"Opponent name":"RSA","Period":4.0,"Player":"HOSOYA K","Score":"5 - 14","Seconds":250,"Team":"JPN","Time":"4:10","Result":"Goal","Goal":1},{"Action":"Counter attack","Cap":6.0,"Game":5,"JPN":15,"Opponent":5,"Opponent name":"RSA","Period":4.0,"Player":"TAKAHASHI A","Score":"5 - 15","Seconds":221,"Team":"JPN","Time":"3:41","Result":"Goal","Goal":1},{"Action":"Extra player shot","Cap":5.0,"Game":5,"JPN":15,"Opponent":7,"Opponent name":"RSA","Period":4.0,"Player":"SCHOOLING M","Score":"7 - 15","Seconds":99,"Team":"RSA","Time":"1:39","Result":"Goal","Goal":1},{"Action":"Counter attack","Cap":4.0,"Game":5,"JPN":15,"Opponent":7,"Opponent name":"RSA","Period":4.0,"Player":"MAGARIYAMA S","Score":"7 - 15","Seconds":6,"Team":"JPN","Time":"0:06","Result":"Saved","Goal":0}]